legitindicators.py
legitindicators-0.0.76.dist-info/licenses/LICENSE.txt
legitindicators-0.0.76.dist-info/METADATA
legitindicators-0.0.76.dist-info/WHEEL
legitindicators-0.0.76.dist-info/top_level.txt
legitindicators-0.0.76.dist-info/RECORD
