Metadata-Version: 2.4
Name: legitindicators
Version: 0.0.76
Summary: Legit indicators to be used in trading strategies.
Home-page: https://github.com/aticio/legitindicators
Author: Özgür Atıcı
Author-email: aticiozgur@gmail.com
Classifier: Programming Language :: Python :: 3
Classifier: License :: OSI Approved :: MIT License
Classifier: Operating System :: OS Independent
License-File: LICENSE.txt
Requires-Dist: numpy
Provides-Extra: dev
Requires-Dist: pytest>=3.7; extra == "dev"
Dynamic: author
Dynamic: author-email
Dynamic: classifier
Dynamic: description
Dynamic: description-content-type
Dynamic: home-page
Dynamic: license-file
Dynamic: provides-extra
Dynamic: requires-dist
Dynamic: summary
